oddsnends/__init__.py
oddsnends/cli.py
oddsnends/collectionstools.py
oddsnends/intervals.py
oddsnends/ioa.py
oddsnends/main.py
oddsnends/mathtools.py
oddsnends/pdtools.py
oddsnends/.vscode/bookmarks.json
oddsnends/.vscode/settings.json
oddsnends-0.3.2.post1.dist-info/METADATA
oddsnends-0.3.2.post1.dist-info/WHEEL
oddsnends-0.3.2.post1.dist-info/licenses/AUTHORS.rst
oddsnends-0.3.2.post1.dist-info/licenses/LICENSE
oddsnends-0.3.2.post1.dist-info/RECORD
