Metadata-Version: 2.1
Name: oddsnends
Version: 0.3.2.post1
Summary: Miscellaneous (odds 'n ends) methods for data science
Author-email: Vivian Leung <leung.vivian.w@gmail.com>
License: MIT License
License-File: AUTHORS.rst
License-File: LICENSE
Keywords: oddsnends
Classifier: License :: OSI Approved :: MIT License
Classifier: Operating System :: OS Independent
Classifier: Programming Language :: Python :: 3
Classifier: Programming Language :: Python :: 3.10
Classifier: Programming Language :: Python :: 3.11
Classifier: Programming Language :: Python :: 3.12
Requires-Python: >=3.10
Requires-Dist: numpy
Requires-Dist: pandas>=2.1
Requires-Dist: pip>=23.3
Requires-Dist: regex
Provides-Extra: dev
Requires-Dist: bump2version>=0.5.11; extra == 'dev'
Requires-Dist: coverage>=4.5.4; extra == 'dev'
Requires-Dist: doctest; extra == 'dev'
Requires-Dist: flake8>=3.7.8; extra == 'dev'
Requires-Dist: hatch; extra == 'dev'
Requires-Dist: hatch-requirements-txt; extra == 'dev'
Requires-Dist: ipykernel; extra == 'dev'
Requires-Dist: jupyter; extra == 'dev'
Requires-Dist: pip>=23.3; extra == 'dev'
Requires-Dist: pytest-cov>=4.1; extra == 'dev'
Requires-Dist: pytest>=7.4; extra == 'dev'
Requires-Dist: sphinx>=1.8.5; extra == 'dev'
Requires-Dist: tomli; extra == 'dev'
Requires-Dist: tox>=3.14.0; extra == 'dev'
Requires-Dist: twine>=1.14.0; extra == 'dev'
Requires-Dist: watchdog>=0.9.0; extra == 'dev'
Requires-Dist: wheel>=0.38.1; extra == 'dev'
